peprock/dt/__init__.py
peprock/dt/awareness.py
peprock/dt/period.py
peprock/dt/py.typed
peprock/models/__init__.py
peprock/models/measurement.py
peprock/models/metric_prefix.py
peprock/models/py.typed
peprock/models/unit.py
peprock/patterns/__init__.py
peprock/patterns/observer.py
peprock/patterns/py.typed
peprock/subclasses/__init__.py
peprock/subclasses/py.typed
peprock-2.0.0.dist-info/licenses/LICENSE
peprock-2.0.0.dist-info/WHEEL
peprock-2.0.0.dist-info/METADATA
peprock-2.0.0.dist-info/RECORD
