Metadata-Version: 2.4
Name: peprock
Version: 2.0.0
Summary: Foundational Python library
Keywords: peprock,datetime,dt,models,patterns,subclasses
Author: Jakob Keller
Author-email: Jakob Keller <57402305+jakob-keller@users.noreply.github.com>
License-Expression: MIT
License-File: LICENSE
Classifier: Development Status :: 5 - Production/Stable
Classifier: Topic :: Software Development :: Libraries :: Python Modules
Classifier: Intended Audience :: Developers
Classifier: License :: OSI Approved :: MIT License
Classifier: Natural Language :: English
Classifier: Programming Language :: Python :: 3
Classifier: Programming Language :: Python :: 3.10
Classifier: Programming Language :: Python :: 3.11
Classifier: Programming Language :: Python :: 3.12
Classifier: Programming Language :: Python :: 3.13
Classifier: Programming Language :: Python :: 3.14
Classifier: Typing :: Typed
Requires-Dist: typing-extensions>=4.0.1,<5.0.0 ; python_full_version < '3.11'
Requires-Python: >=3.10
Project-URL: Documentation, https://api.peprock.ponte.energy
Project-URL: Ponte Energy Partners, https://ponte.energy
Project-URL: Source Code, https://github.com/Ponte-Energy-Partners/peprock
